Metadata-Version: 2.4
Name: mcp-cuc-wjf
Version: 0.1.0
Summary: 基于 Model Context Protocol 的时间服务，提供获取当前时间的工具
Author-email: Your Name <your.email@example.com>
Keywords: mcp,model-context-protocol,time,server
Requires-Python: >=3.8
License-File: LICENSE
Requires-Dist: fastmcp
Requires-Dist: pytz
Dynamic: license-file
